<?xml version="1.0" encoding="UTF-8"?>
<data>
    <entity>
        <type>2</type>
        <name>Титаник</name>
        <image>titanic.jpg</image>
        <releaseDate>1997-12-19</releaseDate>
    </entity>
    <entity>
        <type>2</type>
        <name>Огнеупорный</name>
        <image>fire.jpg</image>
        <releaseDate>2002-01-10</releaseDate>
    </entity>
    <entity>
        <type>2</type>
        <name>Warcraft</name>
        <image>warcraft.jpg</image>
        <releaseDate>2016-05-24</releaseDate>
    </entity>
    <entity>
        <type>2</type>
        <name>Три мушкетера</name>
        <image>tri.jpg</image>
        <releaseDate>2015-06-15</releaseDate>
    </entity>
    <entity>
        <type>2</type>
        <name>Брюс всемогущий</name>
        <image>brus.jpg</image>
        <releaseDate>2003-05-23</releaseDate>
    </entity>
    <entity>
        <type>1</type>
        <name>Beatles</name>
        <image>beatles.jpg</image>
        <releaseDate>1964-08-08</releaseDate>
        <artist>John Lennon</artist>
    </entity>
    <entity>
        <type>1</type>
        <name>Love</name>
        <image>30.jpg</image>
        <releaseDate>2010-08-16</releaseDate>
        <artist>30 Seconds to Mars</artist>
    </entity>
    <entity>
        <type>1</type>
        <name>Моя любовь</name>
        <image>bas.jpeg</image>
        <releaseDate>2008-08-16</releaseDate>
        <artist>Басков</artist>
    </entity>
    <entity>
        <type>1</type>
        <name>Numb</name>
        <image>numb.jpg</image>
        <releaseDate>2003-10-23</releaseDate>
        <artist>Linkin Park</artist>
    </entity>
    <entity>
        <type>1</type>
        <name>Do hust</name>
        <image>du.jpg</image>
        <releaseDate>1997-10-23</releaseDate>
        <artist>Rammstein</artist>
    </entity>
    <entity>
        <type>3</type>
        <name>День России</name>
        <image>denr.jpeg</image>
        <location>Симферополь, пл. Ленина</location>
        <startDate>2016-06-13 10:00</startDate>
        <endDate>2016-06-13 22:00</endDate>
    </entity>
    <entity>
        <type>3</type>
        <name>Night Party</name>
        <image>party.jpg</image>
        <location>Ibiza</location>
        <startDate>2016-08-22 21:00</startDate>
        <endDate>2016-08-23 06:00</endDate>
    </entity>
    <entity>
        <type>3</type>
        <name>Поход на ЮБК!</name>
        <image>pohod.jpg</image>
        <location>Фиолент</location>
        <startDate>2016-09-01 10:00</startDate>
        <endDate>2016-09-03 17:00</endDate>
    </entity>
    <entity>
        <type>3</type>
        <name>Comedy club</name>
        <image>comedyclub.jpg</image>
        <location>Ялта, гостинница "Интурист"</location>
        <startDate>2016-10-01 19:00</startDate>
        <endDate>2016-10-01 22:00</endDate>
    </entity>
    <entity>
        <type>3</type>
        <name>Снова праздник</name>
        <image>1sen.jpg</image>
        <location>Симферополь, 2-ая гимназия</location>
        <startDate>2016-09-01 08:00</startDate>
        <endDate>2016-09-01 11:00</endDate>
    </entity>
</data>